nodepasta/__init__.py
nodepasta/argtypes.py
nodepasta/errors.py
nodepasta/id_manager.py
nodepasta/node.py
nodepasta/nodegraph.py
nodepasta/ports.py
nodepasta/utils.py
nodepasta/impasta/__init__.py
nodepasta/impasta/imgui_arg_handlers.py
nodepasta/impasta/imgui_node_graph.py
nodepasta/testing/__init__.py
nodepasta/testing/tester.py
nodepasta/tk/__init__.py
nodepasta/tk/tk_arg_handlers.py
nodepasta/tk/tk_node_graph.py
nodepasta-2.0.6.dist-info/licenses/LICENSE
nodepasta-2.0.6.dist-info/METADATA
nodepasta-2.0.6.dist-info/WHEEL
nodepasta-2.0.6.dist-info/top_level.txt
nodepasta-2.0.6.dist-info/RECORD
