Metadata-Version: 2.4
Name: nodepasta
Version: 2.0.6
Summary: A Node Based Visual Scripting System
Author: Alagyn
Project-URL: Repository, https://github.com/alagyn/NodePasta
Project-URL: Issues, https://github.com/alagyn/NodePasta/issues
Classifier: Development Status :: 3 - Alpha
Classifier: Programming Language :: Python :: 3
Classifier: Operating System :: OS Independent
Classifier: Intended Audience :: Developers
Classifier: Topic :: Software Development :: Libraries
Classifier: Typing :: Typed
Classifier: Intended Audience :: Developers
Classifier: Topic :: Software Development :: Libraries
Classifier: Topic :: Software Development :: Libraries :: Python Modules
Classifier: Topic :: Software Development :: User Interfaces
Requires-Python: >=3.7
License-File: LICENSE
Requires-Dist: py-imgui-redux>=3.2.0
Dynamic: license-file
